lranalyzer/__init__.py
lranalyzer/tune/__init__.py
lranalyzer/tune/lr_finder.py
lranalyzer/tune/sanity_check.py
lranalyzer-0.0.4.0.5.dist-info/LICENSE
lranalyzer-0.0.4.0.5.dist-info/METADATA
lranalyzer-0.0.4.0.5.dist-info/WHEEL
lranalyzer-0.0.4.0.5.dist-info/top_level.txt
lranalyzer-0.0.4.0.5.dist-info/RECORD
