Metadata-Version: 2.1
Name: lranalyzer
Version: 0.0.4.0.5
Summary: Learning rate tuning for keras models
Home-page: UNKNOWN
Author: Alec Lumsden
Author-email: aleclumsden@berkeley.edu
License: MIT
Platform: UNKNOWN
Classifier: Development Status :: 4 - Beta
Classifier: License :: OSI Approved :: MIT License
Classifier: Programming Language :: Python
Classifier: Programming Language :: Python :: 3.5
Classifier: Programming Language :: Python :: 3.6
Classifier: Topic :: Software Development :: Libraries
Classifier: Topic :: Software Development :: Libraries :: Python Modules
Classifier: Intended Audience :: Developers
Requires-Python: >=3.5
License-File: LICENSE
Requires-Dist: requests
